LICENSE.txt
linkhub_prometheus_exporter/__init__.py
linkhub_prometheus_exporter/config.py
linkhub_prometheus_exporter/exporter.py
linkhub_prometheus_exporter-0.4.0.dist-info/entry_points.txt
linkhub_prometheus_exporter-0.4.0.dist-info/LICENSE.txt
linkhub_prometheus_exporter-0.4.0.dist-info/WHEEL
linkhub_prometheus_exporter-0.4.0.dist-info/METADATA
linkhub_prometheus_exporter-0.4.0.dist-info/RECORD
