Metadata-Version: 2.1
Name: linkhub-prometheus-exporter
Version: 0.4.0
Summary: A Prometheus metrics exporter for Alcatel Linkhub 4G router boxes
Home-page: https://github.com/imrehg/linkhub_prometheus_exporter
License: Apache-2.0
Author: Gergely Imreh
Author-email: gergely@imreh.net
Requires-Python: >=3.10,<4.0
Classifier: Development Status :: 3 - Alpha
Classifier: Framework :: Pytest
Classifier: Intended Audience :: Information Technology
Classifier: Intended Audience :: System Administrators
Classifier: License :: OSI Approved :: Apache Software License
Classifier: Natural Language :: English
Classifier: Operating System :: OS Independent
Classifier: Programming Language :: Python :: 3
Classifier: Programming Language :: Python :: 3.10
Classifier: Topic :: System :: Monitoring
Classifier: Topic :: System :: Networking :: Monitoring
Classifier: Typing :: Typed
Requires-Dist: dynaconf (>=3.1.8,<4.0.0)
Requires-Dist: jsonrpcclient (>=4.0.2,<5.0.0)
Requires-Dist: prometheus-client (>=0.14.1,<0.15.0)
Requires-Dist: requests (>=2.27.1,<3.0.0)
Requires-Dist: types-requests (>=2.27.25,<3.0.0)
Project-URL: Bug Tracker, https://github.com/imrehg/linkhub_prometheus_exporter/issues
Project-URL: Repository, https://github.com/imrehg/linkhub_prometheus_exporter
